AUTHORS.rst
CONTRIBUTING.rst
HISTORY.rst
LICENSE
MANIFEST.in
README.rst
setup.cfg
setup.py
docs/Makefile
docs/authors.rst
docs/conf.py
docs/contributing.rst
docs/history.rst
docs/index.rst
docs/installation.rst
docs/make.bat
docs/readme.rst
docs/usage.rst
interledger/__init__.py
interledger/cli.py
interledger/interledger.py
interledger.egg-info/PKG-INFO
interledger.egg-info/SOURCES.txt
interledger.egg-info/dependency_links.txt
interledger.egg-info/entry_points.txt
interledger.egg-info/not-zip-safe
interledger.egg-info/top_level.txt
tests/__init__.py
tests/test_interledger.py