Metadata-Version: 1.2
Name: interledger
Version: 0.1.0
Summary: An easy-to-use, high-performance Interledger implementation written in Python
Home-page: https://github.com/ojengwa/interledger
Author: Bernard Ojengwa
Author-email: bernardojengwa@gmail.com
License: MIT license
Keywords: interledger
Platform: UNKNOWN
Classifier: Development Status :: 2 - Pre-Alpha
Classifier: Intended Audience :: Developers
Classifier: License :: OSI Approved :: MIT License
Classifier: Natural Language :: English
Classifier: Programming Language :: Python :: 3
Classifier: Programming Language :: Python :: 3.5
Classifier: Programming Language :: Python :: 3.6
Classifier: Programming Language :: Python :: 3.7
Classifier: Programming Language :: Python :: 3.8
Requires-Python: >=3.5
